LICENSE
MANIFEST.in
README.rst
setup.py
bayesmark/__init__.py
bayesmark/abstract_optimizer.py
bayesmark/cmd_parse.py
bayesmark/constants.py
bayesmark/data.py
bayesmark/expected_max.py
bayesmark/experiment.py
bayesmark/experiment_aggregate.py
bayesmark/experiment_analysis.py
bayesmark/experiment_baseline.py
bayesmark/experiment_db_init.py
bayesmark/experiment_launcher.py
bayesmark/np_util.py
bayesmark/path_util.py
bayesmark/quantiles.py
bayesmark/random_search.py
bayesmark/serialize.py
bayesmark/signatures.py
bayesmark/sklearn_funcs.py
bayesmark/space.py
bayesmark/stats.py
bayesmark/util.py
bayesmark/version.py
bayesmark/xr_util.py
bayesmark.egg-info/PKG-INFO
bayesmark.egg-info/SOURCES.txt
bayesmark.egg-info/dependency_links.txt
bayesmark.egg-info/entry_points.txt
bayesmark.egg-info/requires.txt
bayesmark.egg-info/top_level.txt
bayesmark/builtin_opt/__init__.py
bayesmark/builtin_opt/config.py
bayesmark/builtin_opt/hyperopt_optimizer.py
bayesmark/builtin_opt/nevergrad_optimizer.py
bayesmark/builtin_opt/opentuner_optimizer.py
bayesmark/builtin_opt/pysot_optimizer.py
bayesmark/builtin_opt/random_optimizer.py
bayesmark/builtin_opt/scikit_optimizer.py
requirements/base.in
requirements/ipynb.in
requirements/optimizers.in