Metadata-Version: 2.1
Name: bayesmark
Version: 0.0.5
Summary: Bayesian optimization benchmark system
Home-page: https://github.com/uber/bayesmark/
Author: Ryan Turner
Author-email: rdturnermtl@github.com
License: Apache v2
Platform: any
Provides-Extra: optimizers
Provides-Extra: notebooks
